bayhess/__init__.py
bayhess/bayhess.py
bayhess/cg.py
bayhess/distributions.py
bayhess/newton.py
bayhess-0.1.8.dist-info/LICENSE
bayhess-0.1.8.dist-info/METADATA
bayhess-0.1.8.dist-info/WHEEL
bayhess-0.1.8.dist-info/top_level.txt
bayhess-0.1.8.dist-info/RECORD
