Metadata-Version: 2.1
Name: bayhess
Version: 0.1.8
Summary: Bayesian Hessian Approximation for Stochastic Optimization
Home-page: https://github.com/agcarlon/bayhess
Author: Andre Gustavo Carlon
Author-email: agcarlon@gmail.com
License: GPLv3
Project-URL: Documentation, https://bayhess.readthedocs.io/
Project-URL: Source, https://github.com/agcarlon/bayhess
Project-URL: Manuscript, https://arxiv.org/abs/2208.00441
Keywords: stochastic optimization,Bayesian inference
Classifier: Development Status :: 4 - Beta
Classifier: Intended Audience :: Science/Research
Classifier: Intended Audience :: Education
Classifier: Intended Audience :: Information Technology
Classifier: Topic :: Scientific/Engineering
Classifier: Topic :: Education
Classifier: Topic :: Utilities
Classifier: License :: OSI Approved :: GNU General Public License v3 (GPLv3)
Classifier: Programming Language :: Python :: 3
Classifier: Programming Language :: Python :: 3.6
Classifier: Programming Language :: Python :: 3.7
Classifier: Programming Language :: Python :: 3.8
Classifier: Programming Language :: Python :: 3.9
Classifier: Programming Language :: Python :: 3 :: Only
License-File: LICENSE
Requires-Dist: numpy (>=1.19)
Requires-Dist: scipy (>=1.7.1)
